emailxtract/__init__.py
emailxtract/main.py
emailxtract/scraper.py
EmailXtract-1.0.0.dist-info/METADATA
EmailXtract-1.0.0.dist-info/WHEEL
EmailXtract-1.0.0.dist-info/top_level.txt
EmailXtract-1.0.0.dist-info/RECORD
